recap_utils/__init__.py
recap_utils/__main__.py
recap_utils/app.py
recap_utils/graph.py
recap_utils/graph_translator.py
recap_utils/model.py
recap_utils/py.typed
recap_utils/text.py
recap_utils-0.2.1.dist-info/entry_points.txt
recap_utils-0.2.1.dist-info/LICENSE
recap_utils-0.2.1.dist-info/WHEEL
recap_utils-0.2.1.dist-info/METADATA
recap_utils-0.2.1.dist-info/RECORD
