Metadata-Version: 2.1
Name: recap-utils
Version: 0.2.1
Summary: 
Author: Mirko Lenz
Author-email: info@mirko-lenz.de
Requires-Python: >=3.8,<4.0
Classifier: Programming Language :: Python :: 3
Classifier: Programming Language :: Python :: 3.10
Classifier: Programming Language :: Python :: 3.8
Classifier: Programming Language :: Python :: 3.9
Requires-Dist: arg-services (>=0.1.18,<0.2.0)
Requires-Dist: arguebuf (>=0.2.3,<0.3.0)
Requires-Dist: deepl-pro (>=0.1.4,<0.2.0)
Requires-Dist: tomlkit (>=0.7,<0.8)
Requires-Dist: typer (>=0.3.2,<0.4.0)
